easy_excel_tool/__init__.py
easy_excel_tool/excel.py
easy_excel_tool-1.0.5.dist-info/LICENSE
easy_excel_tool-1.0.5.dist-info/METADATA
easy_excel_tool-1.0.5.dist-info/WHEEL
easy_excel_tool-1.0.5.dist-info/top_level.txt
easy_excel_tool-1.0.5.dist-info/RECORD
