Metadata-Version: 2.1
Name: easy-excel-tool
Version: 1.0.5
Summary: 简易、好用的excel操作工具，兼具增删改查，表合并，导出等功能
Home-page: https://easy-excel-tool.xink.top/
Author: hanxinkong
Author-email: xinkonghan@gmail.com
License: MIT
Keywords: easy,excel,tool
Requires-Python: >=3.6.8
License-File: LICENSE
Requires-Dist: openpyxl (==3.1.2)
Requires-Dist: pandas (==1.3.5)
